mcwiki/__init__.py
mcwiki/extractor.py
mcwiki/page.py
mcwiki/py.typed
mcwiki/text.py
mcwiki/tree.py
mcwiki/utils.py
mcwiki-0.2.1.dist-info/LICENSE
mcwiki-0.2.1.dist-info/WHEEL
mcwiki-0.2.1.dist-info/METADATA
mcwiki-0.2.1.dist-info/RECORD
