Metadata-Version: 2.1
Name: mcwiki
Version: 0.2.1
Summary: A scraping library for the Minecraft Wiki
Home-page: https://github.com/vberlier/mcwiki
License: MIT
Keywords: mcwiki,minecraft,scraping,wiki,minecraft-wiki
Author: Valentin Berlier
Author-email: berlier.v@gmail.com
Requires-Python: >=3.8,<4.0
Classifier: License :: OSI Approved :: MIT License
Classifier: Programming Language :: Python :: 3
Classifier: Programming Language :: Python :: 3.8
Classifier: Programming Language :: Python :: 3.9
Requires-Dist: beautifulsoup4 (>=4.9.3,<5.0.0)
Requires-Dist: requests (>=2.26.0,<3.0.0)
Project-URL: Documentation, https://github.com/vberlier/mcwiki
Project-URL: Repository, https://github.com/vberlier/mcwiki
